z3c/saconfig/README.rst
z3c/saconfig/__init__.py
z3c/saconfig/interfaces.py
z3c/saconfig/meta.zcml
z3c/saconfig/scopedsession.py
z3c/saconfig/tests.py
z3c/saconfig/utility.py
z3c/saconfig/zcml.py
z3c_saconfig-2.0.dist-info/licenses/LICENSE.rst
z3c_saconfig-2.0.dist-info/METADATA
z3c_saconfig-2.0.dist-info/WHEEL
z3c_saconfig-2.0.dist-info/top_level.txt
z3c_saconfig-2.0.dist-info/RECORD
