Metadata-Version: 2.4
Name: z3c.saconfig
Version: 2.0
Summary: Minimal SQLAlchemy ORM session configuration for Zope
Home-page: https://github.com/zopefoundation/z3c.saconfig/
Author: Martijn Faassen
Author-email: faassen@startifact.com
License: ZPL-2.1
Keywords: zope relational sqlalchemy component integration
Classifier: Development Status :: 4 - Beta
Classifier: Environment :: Web Environment
Classifier: Framework :: Zope :: 3
Classifier: Framework :: Zope :: 4
Classifier: Intended Audience :: Developers
Classifier: License :: OSI Approved :: Zope Public License
Classifier: Operating System :: OS Independent
Classifier: Programming Language :: Python :: 3.9
Classifier: Programming Language :: Python :: 3.10
Classifier: Programming Language :: Python :: 3.11
Classifier: Programming Language :: Python :: 3.12
Classifier: Programming Language :: Python :: 3.13
Classifier: Programming Language :: Python :: Implementation :: CPython
Classifier: Topic :: Internet :: WWW/HTTP
Classifier: Topic :: Software Development :: Libraries
Classifier: Topic :: Database
Requires-Python: >=3.9
License-File: LICENSE.rst
Requires-Dist: setuptools
Requires-Dist: zope.sqlalchemy>=0.5
Requires-Dist: zope.interface
Requires-Dist: zope.component
Requires-Dist: zope.hookable
Requires-Dist: zope.security
Requires-Dist: zope.event
Requires-Dist: zope.configuration
Provides-Extra: test
Requires-Dist: zope.testing; extra == "test"
Dynamic: author
Dynamic: author-email
Dynamic: classifier
Dynamic: description
Dynamic: home-page
Dynamic: keywords
Dynamic: license
Dynamic: license-file
Dynamic: provides-extra
Dynamic: requires-dist
Dynamic: requires-python
Dynamic: summary
